<?xml version="1.0" encoding="UTF-8"?>
<objects serializationModel="Studio.02.02.00">
	<object class="AudioFile" id="{a9fb2d75-4bff-4095-bf50-e229d398e027}">
		<property name="assetPath">
			<value>PaperSounds/Paper4.wav</value>
		</property>
		<property name="frequencyInKHz">
			<value>48</value>
		</property>
		<property name="channelCount">
			<value>2</value>
		</property>
		<property name="length">
			<value>2.5</value>
		</property>
		<relationship name="masterAssetFolder">
			<destination>{a386d213-8f83-46c8-926a-4aa2b2e84890}</destination>
		</relationship>
	</object>
</objects>
